MANIFEST.in
README.rst
setup.cfg
setup.py
c2c/__init__.py
c2c.recipe.pkgversions.egg-info/PKG-INFO
c2c.recipe.pkgversions.egg-info/SOURCES.txt
c2c.recipe.pkgversions.egg-info/dependency_links.txt
c2c.recipe.pkgversions.egg-info/entry_points.txt
c2c.recipe.pkgversions.egg-info/not-zip-safe
c2c.recipe.pkgversions.egg-info/requires.txt
c2c.recipe.pkgversions.egg-info/top_level.txt
c2c/recipe/__init__.py
c2c/recipe/pkgversions/__init__.py