Metadata-Version: 1.1
Name: c2c.recipe.pkgversions
Version: 0.3dev1
Summary: Test dependencies on Debian package versions
Home-page: http://github.com/sbrunner/c2c.recipe.pkgversions
Author: Stéphane Brunner
Author-email: stephane.brunner@camptocamp.com
License: BSD
Keywords: debian package versons
Platform: UNKNOWN
Classifier: Development Status :: 4 - Beta
Classifier: Environment :: Console
Classifier: Intended Audience :: Developers
Classifier: License :: OSI Approved :: BSD License
Classifier: Programming Language :: Python
Classifier: Framework :: Buildout :: Recipe
Classifier: Topic :: System :: Installation/Setup
